ipe/__init__.py
ipe/attention.py
ipe/experiment.py
ipe/graph_search.py
ipe/metrics.py
ipe/miscellanea.py
ipe/nodes.py
ipe/paths.py
ipe/plot/decoding_plot.py
ipe/plot/graph_plot.py
ipe/webutils/image_nodes.py
ipe/webutils/model.py
ipe-0.0.1.dist-info/licenses/LICENSE.txt
ipe-0.0.1.dist-info/METADATA
ipe-0.0.1.dist-info/WHEEL
ipe-0.0.1.dist-info/top_level.txt
ipe-0.0.1.dist-info/RECORD
