Metadata-Version: 2.4
Name: ipe
Version: 0.0.1
Summary: Implementation of IPE: Isolating Path Effect for Latent Circuit Identification. This module implements an interface to handle complex patching of transformer nodes, a path-wise backpropagation algorithm and various graph search strategies to identify task specific circuits in transformer models.
Author-email: Andrea Cerutti <andrea01.cerutti@gmail.com>
License-Expression: MIT
Project-URL: Homepage, https://github.com/andreac01/IPE-LatentCircuitIdentification
Project-URL: Documentation, https://ipe-documentation.ceru-sh.site/
Project-URL: Bug Tracker, https://github.com/andreac01/IPE-LatentCircuitIdentification/issues
Keywords: llm,interpretability,circuits,computational paths
Classifier: Programming Language :: Python :: 3
Requires-Python: >=3.12
License-File: LICENSE.txt
Requires-Dist: einops
Requires-Dist: torch
Requires-Dist: transformer-lens
Requires-Dist: matplotlib
Requires-Dist: tqdm
Requires-Dist: numpy
Requires-Dist: pytest
Requires-Dist: plotly
Requires-Dist: ipywidgets
Dynamic: license-file
